antchain_sdk_ak_330f8644fede4163afd908d29b373e6a/__init__.py
antchain_sdk_ak_330f8644fede4163afd908d29b373e6a/client.py
antchain_sdk_ak_330f8644fede4163afd908d29b373e6a/models.py
antchain_ak_330f8644fede4163afd908d29b373e6a-1.0.0.dist-info/LICENSE
antchain_ak_330f8644fede4163afd908d29b373e6a-1.0.0.dist-info/METADATA
antchain_ak_330f8644fede4163afd908d29b373e6a-1.0.0.dist-info/WHEEL
antchain_ak_330f8644fede4163afd908d29b373e6a-1.0.0.dist-info/top_level.txt
antchain_ak_330f8644fede4163afd908d29b373e6a-1.0.0.dist-info/RECORD
